kamikaze-0.1.1.data/scripts/kamikaze
kamikaze-0.1.1.dist-info/top_level.txt
kamikaze-0.1.1.dist-info/metadata.json
kamikaze-0.1.1.dist-info/DESCRIPTION.rst
kamikaze-0.1.1.dist-info/RECORD
kamikaze-0.1.1.dist-info/WHEEL
kamikaze-0.1.1.dist-info/METADATA
kamikaze/__main__.py
kamikaze/service.py
kamikaze/__init__.py
kamikaze/_version.py
kamikaze/operations.py
kamikaze/utils.py
