Metadata-Version: 2.0
Name: kamikaze
Version: 0.1.1
Summary: A service for placing prioritised packages with expiry times on a queue and having a consumer notified of the packages
Home-page: https://github.com/brendanmaguire/kamikaze
Author: Brendan Maguire
Author-email: maguire.brendan@gmail.com
License: BSD
Keywords: kamikaze
Platform: UNKNOWN
Classifier: License :: OSI Approved :: BSD License
Classifier: Natural Language :: English
Classifier: Programming Language :: Python :: 3.3
Classifier: Programming Language :: Python :: 3.4
Requires-Dist: argh (==0.26.1)
Requires-Dist: asyncio-redis (==0.13.4)
Requires-Dist: redis (==2.10.3)
Requires-Dist: tabulate (==0.7.3)
Requires-Dist: wheel (==0.24.0)
